odoo/addons/pos_backend_communication/README.rst
odoo/addons/pos_backend_communication/__init__.py
odoo/addons/pos_backend_communication/__manifest__.py
odoo/addons/pos_backend_communication/i18n/es.po
odoo/addons/pos_backend_communication/i18n/it.po
odoo/addons/pos_backend_communication/i18n/pos_backend_communication.pot
odoo/addons/pos_backend_communication/models/__init__.py
odoo/addons/pos_backend_communication/models/ir_action.py
odoo/addons/pos_backend_communication/security/ir.model.access.csv
odoo/addons/pos_backend_communication/static/description/icon.png
odoo/addons/pos_backend_communication/static/src/css/pos_backend_communication.css
odoo/addons/pos_backend_communication/static/src/js/back.js
odoo/addons/pos_backend_communication/static/src/js/common.js
odoo/addons/pos_backend_communication/views/assets.xml
odoo14_addon_pos_backend_communication-14.0.1.0.1.dist-info/METADATA
odoo14_addon_pos_backend_communication-14.0.1.0.1.dist-info/WHEEL
odoo14_addon_pos_backend_communication-14.0.1.0.1.dist-info/top_level.txt
odoo14_addon_pos_backend_communication-14.0.1.0.1.dist-info/RECORD
